icaras_verilog/Circuit Design 1/assigning.v
module inpoutp( 
	input A, 
	input B, 
	input C, 
	input D, 
	output Z
	);
assign Z=(A & B & C & ~D)|(~A & B & ~C & ~D);

endmodule

icaras_verilog/Circuit Design 1/stimulus.v
`timescale 1ns/1ps
module stimulus;
	reg A;
	reg B;
	reg C;
	reg D;
	wire Z;
	
	inpoutp uut( .A(A), .B(B), .C(C), .D(D), .Z(Z));
	initial begin
	
		A=0;
		B=0;
		C=0;
		D=0;
		#20 B=1;
		#20 A=1;
		#20 C=1;
		#20 D=1;
		#20 A=0;
		#20 B=0;
		#20 C=0;
		#20 A=1;
		#20 B=1;
		#20 A=0;
		#40;
	end
	initial begin
		 $monitor("A=%d, B=%d, C=%d, D=%d, Z=%d \n",A,B,C,D,Z);
		 end
 
endmodule

icaras_verilog/Circuit Design 1/test.vcd
$date
	Sat Dec 05 18:21:24 2020
$end
$version
	Icarus Verilog
$end
$timescale
	1ps
$end
$scope module stimulus $end
$var wire 1 ! Z $end
$var reg 1 " A $end
$var reg 1 # B $end
$var reg 1 $ C $end
$var reg 1 % D $end
$scope module uut $end
$var wire 1 " A $end
$var wire 1 # B $end
$var wire 1 $ C $end
$var wire 1 % D $end
$var wire 1 ! Z $end
$upscope $end
$upscope $end
$enddefinitions $end
#0
$dumpvars
0%
0$
0#
0"
0!
$end
#20000
1!
1#
#40000
0!
1"
#60000
1!
1$
#80000
0!
1%
#100000
0"
#120000
0#
#140000
0$
#160000
1"
#180000
1#
#200000
0"
